portafilter/__init__.py
portafilter/decorators.py
portafilter/enums.py
portafilter/exceptions.py
portafilter/json_parser.py
portafilter/json_schema.py
portafilter/rules.py
portafilter/sandglass.py
portafilter/translator.py
portafilter/utils.py
portafilter/validator.py
portafilter/cli/__init__.py
portafilter/cli/main.py
portafilter/languages/en.json
tests/__init__.py
tests/run_tests.py
tests/test_after_or_equal_rule.py
tests/test_after_rule.py
tests/test_before_or_equal_rule.py
tests/test_before_rule.py
tests/test_boolean_rule.py
tests/test_custom_rule.py
tests/test_custom_ruleset.py
tests/test_date_rule.py
tests/test_different_rule.py
tests/test_email_rule.py
tests/test_in_rule.py
tests/test_integer_rule.py
tests/test_list_rule.py
tests/test_max_rule.py
tests/test_min_rule.py
tests/test_not_in_rule.py
tests/test_numeric_rule.py
tests/test_required_rule.py
tests/test_same_rule.py
tests/test_size_rule.py
tests/test_string_rule.py
tests/utils.py
portafilter-1.0.1.dist-info/LICENSE
portafilter-1.0.1.dist-info/METADATA
portafilter-1.0.1.dist-info/WHEEL
portafilter-1.0.1.dist-info/top_level.txt
portafilter-1.0.1.dist-info/RECORD
