Metadata-Version: 2.1
Name: portafilter
Version: 1.0.1
Summary: Portafilter provides powerful and simple data validation functionality.
Author: Aryan Arabshahi
Author-email: aryan.arabshahi.programmer@gmail.com
Project-URL: Homepage, https://codewithcoffee.dev
Project-URL: Source Code, https://github.com/aryan-arabshahi/portafilter
Project-URL: Documentation, https://portafilter.dev
Requires-Python: >=3.6
License-File: LICENSE
